{"GlobalPropertiesHash":"lhSFHnHCiN7XXAqDt1reYE3lRowo5Mx6cc8FwQYl2Rg=","FingerprintPatternsHash":"gq3WsqcKBUGTSNle7RKKyXRIwh7M8ccEqOqYvIzoM04=","PropertyOverridesHash":"8ZRc1sGeVrPBx4lD717BgRaQekyh78QKV9SKsdt638U=","InputHashes":["D6qMZSzJhcec1aQuORPNXBzKvJmaic9BAMO6ULdYsYY=","HsAEoVm3AckJ/zduNIxOYJMPrG8yaWLY4UPy0Mkp4n4=","f\u002B9HlLofWEc7xNLHX7zX\u002BofBuKG5Q7cCRMh0m0xwOLc="],"CachedAssets":{"D6qMZSzJhcec1aQuORPNXBzKvJmaic9BAMO6ULdYsYY=":{"Identity":"C:\\Users\\Jelle\\source\\repos\\HomeInventoryManager\\HomeInventoryManager\\HomeInventoryManager.Web.Client\\wwwroot\\appsettings.Development.json","SourceId":"HomeInventoryManager.Web.Client","SourceType":"Discovered","ContentRoot":"C:\\Users\\Jelle\\source\\repos\\HomeInventoryManager\\HomeInventoryManager\\HomeInventoryManager.Web.Client\\wwwroot\\","BasePath":"/","RelativePath":"appsettings.Development#[.{fingerprint}]?.json","AssetKind":"All","AssetMode":"All","AssetRole":"Primary","AssetMergeBehavior":null,"AssetMergeSource":"","RelatedAsset":null,"AssetTraitName":null,"AssetTraitValue":null,"Fingerprint":"tswichycbp","Integrity":"c/lfngzrIF/BxNxQwHaX/Pop1wh4aMKu8dUEyzjHcew=","CopyToOutputDirectory":"Never","CopyToPublishDirectory":"PreserveNewest","OriginalItemSpec":"wwwroot\\appsettings.Development.json","FileLength":127,"LastWriteTime":"2025-07-18T10:13:30.8223743+00:00"},"HsAEoVm3AckJ/zduNIxOYJMPrG8yaWLY4UPy0Mkp4n4=":{"Identity":"C:\\Users\\Jelle\\source\\repos\\HomeInventoryManager\\HomeInventoryManager\\HomeInventoryManager.Web.Client\\wwwroot\\appsettings.json","SourceId":"HomeInventoryManager.Web.Client","SourceType":"Discovered","ContentRoot":"C:\\Users\\Jelle\\source\\repos\\HomeInventoryManager\\HomeInventoryManager\\HomeInventoryManager.Web.Client\\wwwroot\\","BasePath":"/","RelativePath":"appsettings#[.{fingerprint}]?.json","AssetKind":"All","AssetMode":"All","AssetRole":"Primary","AssetMergeBehavior":null,"AssetMergeSource":"","RelatedAsset":null,"AssetTraitName":null,"AssetTraitValue":null,"Fingerprint":"tswichycbp","Integrity":"c/lfngzrIF/BxNxQwHaX/Pop1wh4aMKu8dUEyzjHcew=","CopyToOutputDirectory":"Never","CopyToPublishDirectory":"PreserveNewest","OriginalItemSpec":"wwwroot\\appsettings.json","FileLength":127,"LastWriteTime":"2025-07-18T10:13:30.8243744+00:00"}},"CachedCopyCandidates":{}}